LICENSE.txt
MANIFEST.in
README.rst
setup.py
onthego/__init__.py
onthego/auth.py
onthego/cli.py
onthego/id3.py
onthego/search.py
onthego/spotify.py
onthego/youtube.py
requirements/base.in
spotify_onthego.egg-info/PKG-INFO
spotify_onthego.egg-info/SOURCES.txt
spotify_onthego.egg-info/dependency_links.txt
spotify_onthego.egg-info/entry_points.txt
spotify_onthego.egg-info/requires.txt
spotify_onthego.egg-info/top_level.txt