Metadata-Version: 2.1
Name: spotify-onthego
Version: 1.0.11
Summary: Download Spotify songs and playlists (with YouTube)
Home-page: https://github.com/regisb/spotify-onthego
Author: Régis Behmo
Author-email: nospam@behmo.com
License: GPL
Keywords: spotify youtube download playlist music songs
Platform: UNKNOWN
Classifier: Programming Language :: Python
Classifier: Programming Language :: Python :: 3.8
Classifier: Programming Language :: Python :: 3.9
Classifier: Programming Language :: Python :: 3.10
Classifier: Programming Language :: Python :: 3.11
Classifier: Programming Language :: Python :: 3.12
Classifier: License :: OSI Approved :: GNU General Public License v3 (GPLv3)
Classifier: Development Status :: 5 - Production/Stable
Classifier: Topic :: Multimedia :: Sound/Audio :: Capture/Recording
License-File: LICENSE.txt
